{
  "version": "0.3.14-fixed",
  "steps": [
    {
      "tag": "CreateModel",
      "model": "Meeting"
    },
    {
      "tag": "CreateField",
      "model": "Meeting",
      "field": "id",
      "type": "Int",
      "arity": "Required"
    },
    {
      "tag": "CreateDirective",
      "location": {
        "path": {
          "tag": "Field",
          "model": "Meeting",
          "field": "id"
        },
        "directive": "id"
      }
    },
    {
      "tag": "CreateDirective",
      "location": {
        "path": {
          "tag": "Field",
          "model": "Meeting",
          "field": "id"
        },
        "directive": "default"
      }
    },
    {
      "tag": "CreateArgument",
      "location": {
        "tag": "Directive",
        "path": {
          "tag": "Field",
          "model": "Meeting",
          "field": "id"
        },
        "directive": "default"
      },
      "argument": "",
      "value": "autoincrement()"
    },
    {
      "tag": "CreateField",
      "model": "Meeting",
      "field": "name",
      "type": "String",
      "arity": "Required"
    },
    {
      "tag": "CreateField",
      "model": "Meeting",
      "field": "link",
      "type": "String",
      "arity": "Required"
    },
    {
      "tag": "CreateField",
      "model": "Meeting",
      "field": "owner",
      "type": "User",
      "arity": "Required"
    },
    {
      "tag": "CreateDirective",
      "location": {
        "path": {
          "tag": "Field",
          "model": "Meeting",
          "field": "owner"
        },
        "directive": "relation"
      }
    },
    {
      "tag": "CreateArgument",
      "location": {
        "tag": "Directive",
        "path": {
          "tag": "Field",
          "model": "Meeting",
          "field": "owner"
        },
        "directive": "relation"
      },
      "argument": "fields",
      "value": "[ownerId]"
    },
    {
      "tag": "CreateArgument",
      "location": {
        "tag": "Directive",
        "path": {
          "tag": "Field",
          "model": "Meeting",
          "field": "owner"
        },
        "directive": "relation"
      },
      "argument": "references",
      "value": "[id]"
    },
    {
      "tag": "CreateField",
      "model": "Meeting",
      "field": "ownerId",
      "type": "Int",
      "arity": "Required"
    },
    {
      "tag": "CreateField",
      "model": "Meeting",
      "field": "description",
      "type": "String",
      "arity": "Required"
    },
    {
      "tag": "CreateField",
      "model": "Meeting",
      "field": "timezone",
      "type": "Int",
      "arity": "Required"
    },
    {
      "tag": "CreateField",
      "model": "Meeting",
      "field": "timeslots",
      "type": "TimeSlot",
      "arity": "List"
    },
    {
      "tag": "CreateModel",
      "model": "TimeSlot"
    },
    {
      "tag": "CreateField",
      "model": "TimeSlot",
      "field": "id",
      "type": "Int",
      "arity": "Required"
    },
    {
      "tag": "CreateDirective",
      "location": {
        "path": {
          "tag": "Field",
          "model": "TimeSlot",
          "field": "id"
        },
        "directive": "id"
      }
    },
    {
      "tag": "CreateDirective",
      "location": {
        "path": {
          "tag": "Field",
          "model": "TimeSlot",
          "field": "id"
        },
        "directive": "default"
      }
    },
    {
      "tag": "CreateArgument",
      "location": {
        "tag": "Directive",
        "path": {
          "tag": "Field",
          "model": "TimeSlot",
          "field": "id"
        },
        "directive": "default"
      },
      "argument": "",
      "value": "autoincrement()"
    },
    {
      "tag": "CreateField",
      "model": "TimeSlot",
      "field": "startTime",
      "type": "DateTime",
      "arity": "Required"
    },
    {
      "tag": "CreateField",
      "model": "TimeSlot",
      "field": "endTime",
      "type": "DateTime",
      "arity": "Required"
    },
    {
      "tag": "CreateField",
      "model": "TimeSlot",
      "field": "meeting",
      "type": "Meeting",
      "arity": "Required"
    },
    {
      "tag": "CreateDirective",
      "location": {
        "path": {
          "tag": "Field",
          "model": "TimeSlot",
          "field": "meeting"
        },
        "directive": "relation"
      }
    },
    {
      "tag": "CreateArgument",
      "location": {
        "tag": "Directive",
        "path": {
          "tag": "Field",
          "model": "TimeSlot",
          "field": "meeting"
        },
        "directive": "relation"
      },
      "argument": "fields",
      "value": "[meetingId]"
    },
    {
      "tag": "CreateArgument",
      "location": {
        "tag": "Directive",
        "path": {
          "tag": "Field",
          "model": "TimeSlot",
          "field": "meeting"
        },
        "directive": "relation"
      },
      "argument": "references",
      "value": "[id]"
    },
    {
      "tag": "CreateField",
      "model": "TimeSlot",
      "field": "meetingId",
      "type": "Int",
      "arity": "Required"
    }
  ]
}